gfxinfo/__init__.py
gfxinfo_mupuf-0.0.9.dist-info/LICENSE
gfxinfo_mupuf-0.0.9.dist-info/METADATA
gfxinfo_mupuf-0.0.9.dist-info/WHEEL
gfxinfo_mupuf-0.0.9.dist-info/top_level.txt
gfxinfo_mupuf-0.0.9.dist-info/RECORD
