Metadata-Version: 2.1
Name: gfxinfo-mupuf
Version: 0.0.9
Summary: Generate a list of tags that describe the environment running a GFX workload
Home-page: https://gitlab.freedesktop.org/mupuf/valve-infra/-/tree/master/gfxinfo
Author: Martin Peres
Author-email: martin.peres@mupuf.org
License: UNKNOWN
Project-URL: Bug Tracker, https://gitlab.freedesktop.org/mupuf/valve-infra/issues
Platform: UNKNOWN
Classifier: Programming Language :: Python :: 3
Classifier: License :: OSI Approved :: MIT License
Classifier: Operating System :: OS Independent
Classifier: Development Status :: 7 - Inactive
Requires-Python: >=3.6
License-File: LICENSE
Requires-Dist: requests (<3,>=2)
Requires-Dist: chturne-vulkan
Requires-Dist: valve-gfx-ci.gfxinfo (>=0.0.9)
Requires-Dist: backports.cached-property ; python_version < "3.8"
